gdg_model_builder/__init__.py
gdg_model_builder/clock/__init__.py
gdg_model_builder/clock/clock.py
gdg_model_builder/clock/predicates.py
gdg_model_builder/clock/predicates__test.py
gdg_model_builder/clock/retro_clock.py
gdg_model_builder/clock/retro_clock__test.py
gdg_model_builder/clock/weakref_clock.py
gdg_model_builder/collection/__init__.py
gdg_model_builder/collection/collection.py
gdg_model_builder/collection/redis_collection.py
gdg_model_builder/collection/redis_collection__test.py
gdg_model_builder/data/__init__.py
gdg_model_builder/data/bufferized.py
gdg_model_builder/model/__init__.py
gdg_model_builder/model/model.py
gdg_model_builder/model/standard_model.py
gdg_model_builder/schedule/__init__.py
gdg_model_builder/schedule/multiplexed_schedule.py
gdg_model_builder/schedule/redis_multiplexed_schedule.py
gdg_model_builder/schedule/redis_multiplexed_schedule__test.py
gdg_model_builder/schedule/redis_schedule.py
gdg_model_builder/schedule/redis_schedule__test.py
gdg_model_builder/schedule/schedule.py
gdg_model_builder/schedule/weakref_schedule.py
gdg_model_builder/shape/__init__.py
gdg_model_builder/shape/pydantic_event.py
gdg_model_builder/shape/pydantic_event__test.py
gdg_model_builder/shape/pydantic_shape.py
gdg_model_builder/shape/pydantic_shape__test.py
gdg_model_builder/shape/shape.py
gdg_model_builder/state/__init__.py
gdg_model_builder/state/redis_state.py
gdg_model_builder/state/state.py
gdg_model_builder/util/__init__.py
gdg_model_builder/util/deasync.py
gdg_model_builder/util/symbol.py
gdg_model_builder/watcher/__init__.py
gdg_model_builder/watcher/redis_watcher.py
gdg_model_builder/watcher/redis_watcher__test.py
gdg_model_builder/watcher/watcher.py
gdg_model_builder-2.3.0.dist-info/WHEEL
gdg_model_builder-2.3.0.dist-info/METADATA
gdg_model_builder-2.3.0.dist-info/RECORD
